django_djazztro/__init__.py
django_djazztro/apps.py
django_djazztro/backends.py
django_djazztro/migrations/__init__.py
django_djazztro-0.3.2.dist-info/METADATA
django_djazztro-0.3.2.dist-info/WHEEL
django_djazztro-0.3.2.dist-info/RECORD
