Metadata-Version: 2.1
Name: django-djazztro
Version: 0.3.2
Summary: Python-side of the Djazztro stack, provides a template backend for using Astro files.
Author: Ben C
Author-email: bwc9876@gmail.com
Requires-Python: >=3.9,<4.0
Classifier: Programming Language :: Python :: 3
Classifier: Programming Language :: Python :: 3.9
Classifier: Programming Language :: Python :: 3.10
Classifier: Programming Language :: Python :: 3.11
Requires-Dist: django (>=4.1.3,<5.0.0)
Requires-Dist: requests (>=2.28.1,<3.0.0)
